
{
  "ID": 141,
  "Name": "obscured_plateau",
  "Resource Location": "midnight:obscured_plateau",
  "Class": "com.mushroom.midnight.common.biome.surface.SurfaceBiome",
  "Root Height": 5.0,
  "Height Variation": 0.01,
  "Top Block": "midnight:nightstone",
  "Filler Block": "midnight:nightstone",
  "Ocean Top Block": "minecraft:gravel",
  "Ocean Filler Block": "minecraft:stone[variant\u003dstone]",
  "Actual Filler Blocks": [
    "minecraft:stone[variant\u003dstone]"
  ],
  "Grass Color": "Not set. Check in-game.",
  "Foliage Color": "Not set. Check in-game.",
  "Water Color": "16777215",
  "Temperature": 0.5,
  "Humidity": 0.5,
  "Water Tint": 16777215,
  "Enable Rain": true,
  "Enable Snow": false,
  "Dictionary Types": [
    "SPOOKY",
    "PLAINS",
    "MOUNTAIN",
    "SPARSE"
  ],
  "BiomeManager Entries": {},
  "Spawnable Creatures": [
    {
      "Entity Class": "pavocado.exoticbirds.entity.Birds.EntityHummingbird",
      "Weight": 18,
      "Min Group Count": 2,
      "Max Group Count": 5
    },
    {
      "Entity Class": "pavocado.exoticbirds.entity.Birds.EntityMagpie",
      "Weight": 12,
      "Min Group Count": 2,
      "Max Group Count": 5
    },
    {
      "Entity Class": "pavocado.exoticbirds.entity.Birds.EntityPeafowl",
      "Weight": 6,
      "Min Group Count": 2,
      "Max Group Count": 5
    },
    {
      "Entity Class": "pavocado.exoticbirds.entity.Birds.EntityPigeon",
      "Weight": 12,
      "Min Group Count": 2,
      "Max Group Count": 5
    },
    {
      "Entity Class": "pavocado.exoticbirds.entity.Birds.EntityCardinal",
      "Weight": 12,
      "Min Group Count": 2,
      "Max Group Count": 5
    },
    {
      "Entity Class": "pavocado.exoticbirds.entity.Birds.EntityBluejay",
      "Weight": 12,
      "Min Group Count": 2,
      "Max Group Count": 5
    },
    {
      "Entity Class": "pavocado.exoticbirds.entity.Birds.EntityRobin",
      "Weight": 12,
      "Min Group Count": 2,
      "Max Group Count": 5
    }
  ],
  "Spawnable Monsters": [
    {
      "Entity Class": "me.suff.angels.common.entities.EntityWeepingAngel",
      "Weight": 50,
      "Min Group Count": 2,
      "Max Group Count": 4
    }
  ],
  "Spawnable Water Creatures": [],
  "Spawnable Cave Creatures": [],
  "Spawn Biome": false,
  "Tweaked": false
}