{
  "key": {
    "id": "Galen5",
    "category": "global"
  },
  "content": {
    "title": "29th April (Galen)",
    "body": "[因 I stumbled upon Pyrrha who seemed to be nervously walking towards her house while holding something with a strong magical aura. [因 seems like the perfect punishment [因 Besides, the philosopher's stone can be really useful for tomorrow night. [因 ",
    "autoplay": true
  },
  "sortingIndex": 35,
  "requirements": [],
  "autoAdd": false,
  "defaultLore": false,
  "trigger": null,
  "action": null
}